README.txt
setup.py
configuration/__init__.py
configuration/configuration.py
configuration.egg-info/PKG-INFO
configuration.egg-info/SOURCES.txt
configuration.egg-info/dependency_links.txt
configuration.egg-info/entry_points.txt
configuration.egg-info/not-zip-safe
configuration.egg-info/requires.txt
configuration.egg-info/top_level.txt