Metadata-Version: 1.0
Name: configuration
Version: 0.4.1
Summary: multi-level unified configuration
Home-page: http://k0s.org/mozilla/hg/configuration
Author: Jeff Hammel
Author-email: jhammel@mozilla.com
License: MPL
Platform: UNKNOWN
